<Properties StartupConfiguration="{2986431F-78F2-4924-A566-8C449E9A1E58}|mid">
  <MonoDevelop.Ide.Workbench ActiveDocument="mid/Views/Home/Index.cshtml">
    <Files>
      <File FileName="mid/Views/Shared/_Layout.cshtml" Line="42" Column="19" />
      <File FileName="mid/Views/Home/Index.cshtml" Line="16" Column="53" />
    </Files>
    <Pads>
      <Pad Id="ProjectPad">
        <State name="__root__">
          <Node name="midtermtask" expanded="True">
            <Node name="midtermtask" expanded="True">
              <Node name="Controllers" expanded="True" />
              <Node name="Models" expanded="True" />
              <Node name="Properties" expanded="True" />
              <Node name="Views" expanded="True">
                <Node name="Calculations" expanded="True" />
                <Node name="Home" expanded="True">
                  <Node name="Index.cshtml" selected="True" />
                </Node>
                <Node name="Shared" expanded="True" />
              </Node>
              <Node name="wwwroot" expanded="True" />
            </Node>
          </Node>
        </State>
      </Pad>
    </Pads>
  </MonoDevelop.Ide.Workbench>
  <MonoDevelop.Ide.ItemProperties.midtermtask PreferredExecutionTarget="/Applications/Safari.app" />
  <MonoDevelop.Ide.DebuggingService.PinnedWatches />
  <MonoDevelop.Ide.Workspace ActiveConfiguration="Debug" />
  <MonoDevelop.Ide.DebuggingService.Breakpoints>
    <BreakpointStore />
  </MonoDevelop.Ide.DebuggingService.Breakpoints>
  <MultiItemStartupConfigurations />
</Properties>